{
  "infile": {
    "chart": {
      "height": 600,
      "width": 600
    },
    "exporting": {
      "sourceHeight": 700,
      "sourceWidth": 700
    },
    "xAxis": {
      "categories": ["Jan", "Feb"]
    },
    "series": [
      {
        "type": "line",
        "data": [1, 3]
      }
    ]
  },
  "svg": "",
  "type": "png",
  "scale": 2,
  "width": 800,
  "height": 800,
  "callback": "function callback(chart){chart.renderer.label('This label is added in the callback.<br>Highcharts version '+Highcharts.version,100,100).attr({fill: '#90ed7d',padding: 10,r: 10,zIndex: 10}).css({color:'black',width:'100px'}).add();}",
  "resources": {
    "js": "Highcharts.charts[0].update({title:{text:'RESOURCES FROM A CUSTOM PATH'}});",
    "css": "@import 'https://code.highcharts.com/css/highcharts.css';g.highcharts-series path { stroke-width: 2; stroke: red; } @import './_ex/_css/style.css';",
    "files": "./_ex/_custom_files/new-options-1.js, ./_ex/_custom_files/new-options-2.js"
  },
  "constr": "chart",
  "b64": false,
  "noDownload": false,
  "globalOptions": {
    "chart": {
      "height": 400,
      "width": 400
    },
    "exporting": {
      "sourceHeight": 500,
      "sourceWidth": 500
    },
    "subtitle": {
      "text": "SUBTITLE"
    }
  },
  "themeOptions": {
    "chart": {
      "backgroundColor": "red"
    }
  },
  "customCode": "function () {Highcharts.setOptions({chart:{borderWidth:2,plotBackgroundColor:'rgba(255, 255, 255, .9)',plotShadow:true,plotBorderWidth:1,events:{render:function() {this.renderer.image('https://www.highcharts.com/samples/graphics/sun.png', 170, 120, 20, 20).add();}}}});}"
}